keycmd/__init__.py
keycmd/cli.py
keycmd/conf.py
keycmd/creds.py
keycmd/logs.py
keycmd/shell.py
keycmd-0.7.0.dist-info/METADATA
keycmd-0.7.0.dist-info/WHEEL
keycmd-0.7.0.dist-info/entry_points.txt
keycmd-0.7.0.dist-info/RECORD
