Metadata-Version: 2.1
Name: keycmd
Version: 0.7.0
Summary: 
License: MIT
Author: Korijn van Golen
Author-email: korijn.vangolen@zimmerbiomet.com
Requires-Python: >=3.9
Classifier: License :: OSI Approved :: MIT License
Classifier: Programming Language :: Python :: 3
Classifier: Programming Language :: Python :: 3.9
Classifier: Programming Language :: Python :: 3.10
Classifier: Programming Language :: Python :: 3.11
Requires-Dist: keyring (>=24.3.0,<25.0.0)
Requires-Dist: shellingham (>=1.5.4,<2.0.0)
Requires-Dist: tomli (>=2.0.1,<3.0.0)
